src/__init__.py
src/phone_footage_sorter/entry.py
tests/__init__.py
tests/conftest.py
tests/test_integration.py
tests/test_system.py
tests/test_unit.py
phone_footage_sorter-1.1.1.dist-info/LICENSE
phone_footage_sorter-1.1.1.dist-info/METADATA
phone_footage_sorter-1.1.1.dist-info/WHEEL
phone_footage_sorter-1.1.1.dist-info/entry_points.txt
phone_footage_sorter-1.1.1.dist-info/top_level.txt
phone_footage_sorter-1.1.1.dist-info/RECORD
