Metadata-Version: 2.1
Name: phone-footage-sorter
Version: 1.1.1
Summary: A simple script to process android phone footage default names into plex-friendly filenames.
Author-email: Benjamin Mummery <benjamin.mummery@zapatacomputing.com>
License: GNU GENERAL PUBLIC LICENSE
Project-URL: Homepage, https://github.com/BenjaminMummery/phone-footage-sorter
Project-URL: Bug Tracker, https://github.com/BenjaminMummery/phone-footage-sorter/issues
Classifier: Programming Language :: Python :: 3
Classifier: Programming Language :: Python :: 3 :: Only
Classifier: Programming Language :: Python :: 3.8
Classifier: Programming Language :: Python :: 3.9
Classifier: Programming Language :: Python :: 3.10
Classifier: Programming Language :: Python :: Implementation :: CPython
Classifier: Programming Language :: Python :: Implementation :: PyPy
Requires-Python: >=3.8
License-File: LICENSE
Provides-Extra: dev
Requires-Dist: build ; extra == 'dev'
Requires-Dist: pytest ; extra == 'dev'
Requires-Dist: pytest-cov ; extra == 'dev'
Requires-Dist: pytest-mock ; extra == 'dev'
Requires-Dist: pytest-virtualenv ; extra == 'dev'
Requires-Dist: python-semantic-release ; extra == 'dev'
